parse_log-1.0.1.dist-info/METADATA
parse_log-1.0.1.dist-info/WHEEL
parse_log-1.0.1.dist-info/license_files/license-mit
tail/__init__.py
tail/tail.cpython-37m-x86_64-linux-gnu.so
parse_log-1.0.1.dist-info/RECORD
