Metadata-Version: 2.1
Name: parse_log
Version: 1.0.1
Classifier: Programming Language :: Rust
Classifier: Programming Language :: Python :: Implementation :: CPython
Classifier: Programming Language :: Python :: Implementation :: PyPy
License-File: license-mit
Summary: Rust tail implementation
Keywords: log,tail,parse,files
Author: killown <developerorprogrammer@gmail.com>
Author-email: killown <developerorprogrammer@gmail.com>
Maintainer-email: killown <developerorprogrammer@gmail.com>
Requires-Python: >=3.7
Project-URL: homepage, https://github.com/killown/parse-log
Project-URL: repository, https://github.com
